chuk_mcp_telnet_client/__init__.py
chuk_mcp_telnet_client/main.py
chuk_mcp_telnet_client/models.py
chuk_mcp_telnet_client/tools.py
chuk_mcp_telnet_client-0.3.1.dist-info/licenses/LICENSE.md
chuk_mcp_telnet_client-0.3.1.dist-info/METADATA
chuk_mcp_telnet_client-0.3.1.dist-info/WHEEL
chuk_mcp_telnet_client-0.3.1.dist-info/entry_points.txt
chuk_mcp_telnet_client-0.3.1.dist-info/top_level.txt
chuk_mcp_telnet_client-0.3.1.dist-info/RECORD
