Metadata-Version: 2.4
Name: chuk-mcp-telnet-client
Version: 0.3.1
Summary: MCP Telnet Client
Requires-Python: >=3.11
License-File: LICENSE.md
Requires-Dist: chuk-mcp-server>=0.15.1
Requires-Dist: pydantic>=2.11.2
Requires-Dist: pyyaml>=6.0.2
Requires-Dist: telnetlib3>=2.0.4
Dynamic: license-file
